[{
    "_id": {
      "$oid": "67cfaf36f4d80646cfd24097"
    },
    "title": "Apple iPhone 17",
    "price": 799.99,
    "category": "electronics"
  },
  {
    "_id": {
      "$oid": "67cfb013b4b45502b7d1bb3a"
    },
    "title": "Apple iPhone 17 Pro",
    "price": 899.99,
    "category": "electronics"
  },
  {
    "_id": {
      "$oid": "67cfb02db4b45502b7d1bb3b"
    },
    "title": "Apple iPhone 17 Pro Max",
    "price": 999.99,
    "category": "electronics"
  },
  {
    "_id": {
      "$oid": "67cfb580ddb7e4c8fb16f456"
    },
    "title": "Apple iPhone 18",
    "price": 1000.99,
    "category": "electronics"
  },
  {
    "_id": {
      "$oid": "67cfc536583daa662a0110b4"
    },
    "title": "Running Shoes",
    "category": "fashion",
    "price": 89.99
  },
  {
    "_id": {
      "$oid": "67cfc536583daa662a0110b5"
    },
    "title": "Leather Jacket",
    "category": "fashion",
    "price": 250
  },
  {
    "_id": {
      "$oid": "67cfc536583daa662a0110b6"
    },
    "title": "Blender",
    "category": "kitchen",
    "price": 59.99
  },
  {
    "_id": {
      "$oid": "67cfc536583daa662a0110b7"
    },
    "title": "Microwave",
    "category": "kitchen",
    "price": 120
  },
  {
    "_id": {
      "$oid": "67cfc536583daa662a0110b8"
    },
    "title": "Bluetooth Headphones",
    "category": "electronics",
    "price": 149.99
  }]